assets/arrow.mtl
assets/arrow.obj
assets/Gallileo.webm
assets/tmp.tmp
bpsci/__init__.py
bpsci/assets/objects/arrow.mtl
bpsci/assets/objects/arrow.obj
bpsci/core.py
bpsci/utils.py
bpsci-0.3.62.dist-info/WHEEL
bpsci-0.3.62.dist-info/METADATA
bpsci-0.3.62.dist-info/RECORD
